icrlearn/__init__.py
icrlearn/_icr.py
icrlearn/py.typed
icrlearn/rarity/__init__.py
icrlearn/rarity/_cb_loop.py
icrlearn/rarity/_l2class.py
icrlearn/tests/__init__.py
icrlearn/tests/test_common.py
icrlearn/tests/test_icr_rf.py
icrlearn/tests/test_rarity.py
icrlearn/utils/__init__.py
icrlearn/utils/discovery.py
icrlearn/utils/tests/__init__.py
icrlearn/utils/tests/test_discovery.py
icrlearn-0.0.1.dist-info/METADATA
icrlearn-0.0.1.dist-info/WHEEL
icrlearn-0.0.1.dist-info/licenses/LICENSE
icrlearn-0.0.1.dist-info/RECORD
