Metadata-Version: 2.4
Name: icrlearn
Version: 0.0.1
Summary: A scikit-learn compatible package for intra-class rarity models.
Project-URL: Homepage, https://github.com/jannewer/intra-class-rare-learn
Project-URL: Issues, https://github.com/jannewer/intra-class-rare-learn/issues
Author-email: Janne Wernecken <dev@wernecken.com>
License-File: LICENSE
Classifier: License :: OSI Approved :: BSD License
Classifier: Operating System :: MacOS
Classifier: Operating System :: Microsoft :: Windows
Classifier: Operating System :: POSIX
Classifier: Operating System :: Unix
Classifier: Programming Language :: Python :: 3
Classifier: Programming Language :: Python :: 3.9
Classifier: Programming Language :: Python :: 3.10
Classifier: Programming Language :: Python :: 3.11
Classifier: Programming Language :: Python :: 3.12
Requires-Python: >=3.10
Requires-Dist: numba>=0.60.0
Requires-Dist: numpy>=2.2.6
Requires-Dist: pandas>=2.3.1
Requires-Dist: pynomaly>=0.3.4
Requires-Dist: scikit-learn>=1.7.1
